Metadata-Version: 2.1
Name: KoGaMa.py-Rewrite
Version: 0.6
Summary: KoGaMa.py-Rewrite is an API-Wrapper for the KoGaMa Website API.
Home-page: https://github.com/TheNoobPro44/KoGaMa.py-Rewrite/
Author: TheNoobPro44
License: MIT
Project-URL: Documentation, https://thenoobpro44.gitbook.io/kogama-py-rewrite/
Project-URL: Bug Tracker, https://github.com/TheNoobPro44/KoGaMa.py-Rewrite/issues
Platform: UNKNOWN
Classifier: Development Status :: 5 - Production/Stable
Classifier: Programming Language :: Python :: 3.9
Classifier: License :: OSI Approved :: MIT License
Classifier: Operating System :: OS Independent
License-File: LICENSE
